dbbasic_logs/__init__.py
dbbasic_logs-1.0.0.dist-info/licenses/LICENSE
tests/__init__.py
tests/test_logging.py
dbbasic_logs-1.0.0.dist-info/METADATA
dbbasic_logs-1.0.0.dist-info/WHEEL
dbbasic_logs-1.0.0.dist-info/top_level.txt
dbbasic_logs-1.0.0.dist-info/RECORD
