Metadata-Version: 2.4
Name: dbbasic-logs
Version: 1.0.0
Summary: Structured logging with TSV storage and compression
Home-page: https://github.com/askrobots/dbbasic-logs
Author: DBBasic Project
Author-email: DBBasic Project <hello@dbbasic.com>
License: MIT
Project-URL: Homepage, https://dbbasic.com
Project-URL: Documentation, https://dbbasic.com/logs-spec
Project-URL: Repository, https://github.com/askrobots/dbbasic-logs
Classifier: Development Status :: 4 - Beta
Classifier: Intended Audience :: Developers
Classifier: License :: OSI Approved :: MIT License
Classifier: Programming Language :: Python :: 3
Requires-Python: >=3.6
License-File: LICENSE
Dynamic: author
Dynamic: home-page
Dynamic: license-file
Dynamic: requires-python
